repoutil/__init__.py
repoutil/gitignores/c.gitignore
repoutil/gitignores/cpp.gitignore
repoutil/gitignores/go.gitignore
repoutil/gitignores/java.gitignore
repoutil/gitignores/node.gitignore
repoutil/gitignores/python.gitignore
repoutil/gitignores/rust.gitignore
repoutil/gitignores/v.gitignore
repoutil/gitignores.py
repoutil/licenses/APACHE.txt
repoutil/licenses/BSD.txt
repoutil/licenses/EPL.txt
repoutil/licenses/GPL.txt
repoutil/licenses/MIT.txt
repoutil/licenses/MPL.txt
repoutil/licenses/UNI.txt
repoutil/licenses.py
repoutil/main.py
repoutil/utils.py
repoutil/workflows/c-cpp.yml
repoutil/workflows/go.yml
repoutil/workflows/node.yml
repoutil/workflows/python.yml
repoutil/workflows/rust.yml
repoutil/workflows.py
repoutil-0.1.0.dist-info/entry_points.txt
repoutil-0.1.0.dist-info/LICENSE.txt
repoutil-0.1.0.dist-info/WHEEL
repoutil-0.1.0.dist-info/METADATA
repoutil-0.1.0.dist-info/RECORD
