Metadata-Version: 2.1
Name: repoutil
Version: 0.1.0
Summary: A simple command line utility to write gitignores, licenses and workflow files to a project.
Home-page: https://bitbucket.org/shravannn/repoutil
License: MIT
Keywords: python,cli,license,gitignore,workflow,repository,write
Author: Shravan Asati
Author-email: dev.shravan@protonmail.com
Requires-Python: >=3.9,<4.0
Classifier: Development Status :: 4 - Beta
Classifier: Environment :: Console
Classifier: Intended Audience :: Developers
Classifier: Intended Audience :: System Administrators
Classifier: License :: OSI Approved :: MIT License
Classifier: Operating System :: OS Independent
Classifier: Programming Language :: Python :: 3
Classifier: Programming Language :: Python :: 3.9
Classifier: Programming Language :: Python :: 3.10
Classifier: Programming Language :: Python :: 3.11
Classifier: Topic :: Software Development :: Build Tools
Classifier: Topic :: Utilities
Requires-Dist: click (>=8.0.1,<9.0.0)
Project-URL: Documentation, https://bitbucket.org/shravannn/repoutil
Project-URL: Repository, https://bitbucket.org/shravannn/repoutil
